octofitterpy/__init__.py
octofitterpy/__main__.py
octofitterpy/julia_helpers.py
octofitterpy/julia_import.py
octofitterpy/juliapkg.json
octofitterpy/python_interface.py
octofitterpy/version.py
octofitterpy-5.2.1.dist-info/LICENSE
octofitterpy-5.2.1.dist-info/METADATA
octofitterpy-5.2.1.dist-info/WHEEL
octofitterpy-5.2.1.dist-info/top_level.txt
octofitterpy-5.2.1.dist-info/RECORD
