Metadata-Version: 2.1
Name: octofitterpy
Version: 5.2.1
Summary: Fast and flexible orbit fitting
Author-email: William Thompson <will.thompson@outlook.com>
License: MIT License
Classifier: Programming Language :: Python :: 3
Classifier: Operating System :: OS Independent
Classifier: License :: OSI Approved :: Apache Software License
Requires-Python: >=3.8
License-File: LICENSE
Requires-Dist: pandas<3.0.0,>=0.21.0
Requires-Dist: numpy<3.0.0,>=1.13.0
Requires-Dist: juliacall==0.9.23
Requires-Dist: setuptools>=50.0.0
